haaslib/__init__.py
haaslib/api.py
haaslib/domain.py
haaslib/iterable_extensions.py
haaslib/lab.py
haaslib/logger.py
haaslib/model.py
haaslib-0.1.0.dist-info/METADATA
haaslib-0.1.0.dist-info/WHEEL
haaslib-0.1.0.dist-info/RECORD
